MANIFEST.in
README.rst
setup.py
django_localflavor_au/__init__.py
django_localflavor_au/admin.py
django_localflavor_au/au_states.py
django_localflavor_au/forms.py
django_localflavor_au/models.py
django_localflavor_au/utils.py
django_localflavor_au_tjh.egg-info/PKG-INFO
django_localflavor_au_tjh.egg-info/SOURCES.txt
django_localflavor_au_tjh.egg-info/dependency_links.txt
django_localflavor_au_tjh.egg-info/requires.txt
django_localflavor_au_tjh.egg-info/top_level.txt