Metadata-Version: 1.1
Name: django-localflavor-au-tjh
Version: 1.1.2
Summary: Country-specific Django helpers for Australia.
Home-page: https://bitbucket.org/tim_heap/django-localflavor-au
Author: Django Software Foundation
Author-email: webmaster@ionata.com.au
License: BSD
Platform: UNKNOWN
Classifier: Development Status :: 5 - Production/Stable
Classifier: Environment :: Web Environment
Classifier: Framework :: Django
Classifier: Intended Audience :: Developers
Classifier: License :: OSI Approved :: BSD License
Classifier: Operating System :: OS Independent
Classifier: Programming Language :: Python
